LICENSE
setup.py
tsc_es/__init__.py
tsc_es/mongo_es.py
tsc_es/user.py
tsc_es.egg-info/PKG-INFO
tsc_es.egg-info/SOURCES.txt
tsc_es.egg-info/dependency_links.txt
tsc_es.egg-info/requires.txt
tsc_es.egg-info/top_level.txt