Metadata-Version: 2.1
Name: tsc-es
Version: 0.12
Summary: mongo to es
Home-page: 
Author: tsc
License: GPLv3
Keywords: tools
Classifier: Intended Audience :: Developers
Classifier: License :: OSI Approved :: GNU General Public License v3 (GPLv3)
Classifier: Programming Language :: Python :: 3 :: Only
Classifier: Topic :: Software Development :: Libraries
Requires-Python: >=3.7
License-File: LICENSE
